darn_dmap-0.7.0.dist-info/METADATA
darn_dmap-0.7.0.dist-info/WHEEL
darn_dmap-0.7.0.dist-info/licenses/COPYING
dmap/__init__.py
dmap/_wrapper.py
dmap/dmap_rs.abi3.so
dmap.libs/libgcc_s-8c2f5de4.so.1
darn_dmap-0.7.0.dist-info/RECORD
