Metadata-Version: 2.4
Name: darn-dmap
Version: 0.7.0
Classifier: Programming Language :: Python
Classifier: Programming Language :: Rust
Requires-Dist: numpy<3
Requires-Dist: pytest ; extra == 'dev'
Requires-Dist: ruff ; extra == 'dev'
Provides-Extra: dev
License-File: COPYING
Summary: SuperDARN DMAP file format I/O
Author: Remington Rohel
License-Expression: LGPL-3.0-or-later
Requires-Python: >=3.8
Project-URL: Repository, https://github.com/SuperDARNCanada/dmap
